pyESMF-8.0.1.4.data/data/esmf/conaninfo.txt
pyESMF-8.0.1.4.data/data/esmf/conanmanifest.txt
pyESMF-8.0.1.4.data/data/esmf/bin/binO/Darwin.gfortran.64.mpiuni.default/ESMF_Info
pyESMF-8.0.1.4.data/data/esmf/bin/binO/Darwin.gfortran.64.mpiuni.default/ESMF_InfoC
pyESMF-8.0.1.4.data/data/esmf/bin/binO/Darwin.gfortran.64.mpiuni.default/ESMF_Regrid
pyESMF-8.0.1.4.data/data/esmf/bin/binO/Darwin.gfortran.64.mpiuni.default/ESMF_RegridWeightGen
pyESMF-8.0.1.4.data/data/esmf/bin/binO/Darwin.gfortran.64.mpiuni.default/ESMF_Scrip2Unstruct
pyESMF-8.0.1.4.data/data/esmf/bin/binO/Darwin.gfortran.64.mpiuni.default/ESMF_WebServController
pyESMF-8.0.1.4.data/data/esmf/include/ESMC.h
pyESMF-8.0.1.4.data/data/esmf/include/ESMC_Arg.h
pyESMF-8.0.1.4.data/data/esmf/include/ESMC_Array.h
pyESMF-8.0.1.4.data/data/esmf/include/ESMC_ArraySpec.h
pyESMF-8.0.1.4.data/data/esmf/include/ESMC_Calendar.h
pyESMF-8.0.1.4.data/data/esmf/include/ESMC_Clock.h
pyESMF-8.0.1.4.data/data/esmf/include/ESMC_Conf.h
pyESMF-8.0.1.4.data/data/esmf/include/ESMC_Config.h
pyESMF-8.0.1.4.data/data/esmf/include/ESMC_CoordSys.h
pyESMF-8.0.1.4.data/data/esmf/include/ESMC_CplComp.h
pyESMF-8.0.1.4.data/data/esmf/include/ESMC_DistGrid.h
pyESMF-8.0.1.4.data/data/esmf/include/ESMC_Field.h
pyESMF-8.0.1.4.data/data/esmf/include/ESMC_Grid.h
pyESMF-8.0.1.4.data/data/esmf/include/ESMC_GridComp.h
pyESMF-8.0.1.4.data/data/esmf/include/ESMC_Init.h
pyESMF-8.0.1.4.data/data/esmf/include/ESMC_Interface.h
pyESMF-8.0.1.4.data/data/esmf/include/ESMC_LocStream.h
pyESMF-8.0.1.4.data/data/esmf/include/ESMC_LogErr.h
pyESMF-8.0.1.4.data/data/esmf/include/ESMC_Macros.h
pyESMF-8.0.1.4.data/data/esmf/include/ESMC_Mesh.h
pyESMF-8.0.1.4.data/data/esmf/include/ESMC_RHandle.h
pyESMF-8.0.1.4.data/data/esmf/include/ESMC_ReturnCodes.h
pyESMF-8.0.1.4.data/data/esmf/include/ESMC_SciComp.h
pyESMF-8.0.1.4.data/data/esmf/include/ESMC_State.h
pyESMF-8.0.1.4.data/data/esmf/include/ESMC_Test.h
pyESMF-8.0.1.4.data/data/esmf/include/ESMC_Time.h
pyESMF-8.0.1.4.dist-info/LICENSE
pyESMF-8.0.1.4.dist-info/METADATA
pyESMF-8.0.1.4.dist-info/WHEEL
pyESMF-8.0.1.4.dist-info/top_level.txt
pyESMF-8.0.1.4.dist-info/RECORD
