Metadata-Version: 2.1
Name: pyESMF
Version: 8.0.1.4
Summary: Python bindings for ESMF
Home-page: https://github.com/Chrismarsh/pyESMF
Author: Chris Marsh
Author-email: chris.marsh@usask.ca
License: UNKNOWN
Platform: UNKNOWN
Requires-Python: >=3.6
Requires-Dist: numpy
